typed_flags/__init__.py
typed_flags/flags.py
typed_flags/py.typed
typed_flags/special_types.py
typed_flags/utils.py
typed_flags-0.1.4.dist-info/LICENSE
typed_flags-0.1.4.dist-info/METADATA
typed_flags-0.1.4.dist-info/WHEEL
typed_flags-0.1.4.dist-info/top_level.txt
typed_flags-0.1.4.dist-info/RECORD
