Metadata-Version: 2.1
Name: typed-flags
Version: 0.1.4
Summary: Typed Flags
Home-page: https://git.sr.ht/~tmk/typed-flags
Author: Thomas Kehrenberg
Author-email: thomas5max@gmail.com
License: Apache
Keywords: typing,argument parser,python
Platform: UNKNOWN
Classifier: Programming Language :: Python :: 3.8
Classifier: License :: OSI Approved :: Apache Software License
Classifier: Operating System :: OS Independent
Classifier: Typing :: Typed
Requires-Python: >=3.8
